{
  "id": "template_listly_tasks",
  "name": "Listly Tasks",
  "description": "Superlist-inspired App Store & Play Store screenshot set. Bold color-blocked panels in coral, purple and green with frameless skeleton app screens so users see exactly how their layout will look.",
  "previewImage": "https://placehold.co/300x200/F1512D/FFFFFF?text=Listly+Tasks",
  "timestamp": "2026-07-07T00:00:00.000Z",
  "projectData": [
    {
      "id": "tpl_lt_ab1",
      "name": "Hero",
      "position": { "x": 15, "y": 15 },
      "size": { "width": 1290, "height": 2796 },
      "backgroundColor": "#E3E3EE",
      "zoom": 1,
      "elements": [
        {
          "id": "tpl_lt_ab1_logo",
          "type": "shape",
          "name": "Logo Icon",
          "position": { "x": 95, "y": 110 },
          "size": { "width": 88, "height": 88 },
          "rotation": 0,
          "scale": 1,
          "shapeType": "rectangle",
          "fillColor": "#5B54D9",
          "strokeColor": "transparent",
          "strokeWidth": 0,
          "borderRadius": 24
        },
        {
          "id": "tpl_lt_ab1_logo_glyph",
          "type": "shape",
          "name": "Logo Glyph",
          "position": { "x": 111, "y": 126 },
          "size": { "width": 56, "height": 56 },
          "rotation": 0,
          "scale": 1,
          "shapeType": "custom-svg",
          "fillColor": "#FFFFFF",
          "strokeColor": "transparent",
          "strokeWidth": 0,
          "customPath": "M28 25 H44 V78 H28 Z M56 38 H72 V78 H56 Z M56 22 H72 V32 H56 Z",
          "specialProps": { "viewBox": "0 0 100 100" }
        },
        {
          "id": "tpl_lt_ab1_wordmark",
          "type": "text",
          "name": "Wordmark",
          "position": { "x": 210, "y": 110 },
          "size": { "width": 500, "height": 88 },
          "rotation": 0,
          "scale": 1,
          "content": "listly",
          "fontSize": 16,
          "color": "#232653",
          "fontFamily": "Bricolage Grotesque",
          "fontWeight": "700",
          "textAlign": "left",
          "lineHeight": 1.1
        },
        {
          "id": "tpl_lt_ab1_headline1",
          "type": "text",
          "name": "Headline Line 1",
          "position": { "x": 95, "y": 330 },
          "size": { "width": 1100, "height": 150 },
          "rotation": 0,
          "scale": 1,
          "content": "Tools with",
          "fontSize": 40,
          "color": "#232653",
          "fontFamily": "Bricolage Grotesque",
          "fontWeight": "700",
          "textAlign": "left",
          "lineHeight": 1.1
        },
        {
          "id": "tpl_lt_ab1_headline2a",
          "type": "text",
          "name": "Headline Accent",
          "position": { "x": 95, "y": 470 },
          "size": { "width": 440, "height": 150 },
          "rotation": 0,
          "scale": 1,
          "content": "Super",
          "fontSize": 40,
          "color": "#F1512D",
          "fontFamily": "Bricolage Grotesque",
          "fontWeight": "700",
          "textAlign": "left",
          "lineHeight": 1.1
        },
        {
          "id": "tpl_lt_ab1_headline2b",
          "type": "text",
          "name": "Headline Line 2",
          "position": { "x": 520, "y": 470 },
          "size": { "width": 620, "height": 150 },
          "rotation": 0,
          "scale": 1,
          "content": "Powers",
          "fontSize": 40,
          "color": "#232653",
          "fontFamily": "Bricolage Grotesque",
          "fontWeight": "700",
          "textAlign": "left",
          "lineHeight": 1.1
        },
        {
          "id": "tpl_lt_ab1_sub",
          "type": "text",
          "name": "Subtitle",
          "position": { "x": 95, "y": 690 },
          "size": { "width": 720, "height": 260 },
          "rotation": 0,
          "scale": 1,
          "content": "Customise, plan,\ncapture and get\nmore done with AI",
          "fontSize": 13,
          "color": "#6E7287",
          "fontFamily": "Bricolage Grotesque",
          "fontWeight": "500",
          "textAlign": "left",
          "lineHeight": 1.3
        },
        {
          "id": "tpl_lt_ab1_back_shadow",
          "type": "shape",
          "name": "Back Screen Shadow",
          "position": { "x": 580, "y": 1400 },
          "size": { "width": 620, "height": 1420 },
          "rotation": 0,
          "scale": 1,
          "shapeType": "rectangle",
          "fillColor": "#232653",
          "strokeColor": "transparent",
          "strokeWidth": 0,
          "borderRadius": 48,
          "fillOpacity": 0.12
        },
        {
          "id": "tpl_lt_ab1_back_screen",
          "type": "image",
          "name": "Back Screen",
          "position": { "x": 580, "y": 1380 },
          "size": { "width": 620, "height": 1420 },
          "rotation": 0,
          "scale": 1,
          "imageSrc": "/data/projects/inboxly-screen-inbox.png",
          "imageAlt": "Skeleton app screen",
          "objectFit": "cover",
          "borderRadius": 48
        },
        {
          "id": "tpl_lt_ab1_front_shadow",
          "type": "shape",
          "name": "Front Screen Shadow",
          "position": { "x": 90, "y": 1540 },
          "size": { "width": 640, "height": 1300 },
          "rotation": 0,
          "scale": 1,
          "shapeType": "rectangle",
          "fillColor": "#232653",
          "strokeColor": "transparent",
          "strokeWidth": 0,
          "borderRadius": 48,
          "fillOpacity": 0.12
        },
        {
          "id": "tpl_lt_ab1_front_screen",
          "type": "image",
          "name": "Front Screen",
          "position": { "x": 90, "y": 1520 },
          "size": { "width": 640, "height": 1300 },
          "rotation": 0,
          "scale": 1,
          "imageSrc": "/data/projects/inboxly-screen-inbox.png",
          "imageAlt": "Skeleton app screen",
          "objectFit": "cover",
          "borderRadius": 48
        }
      ]
    },
    {
      "id": "tpl_lt_ab2",
      "name": "Screens Duo",
      "position": { "x": 417, "y": 15 },
      "size": { "width": 1290, "height": 2796 },
      "backgroundColor": "#E3E3EE",
      "zoom": 1,
      "elements": [
        {
          "id": "tpl_lt_ab2_back_shadow",
          "type": "shape",
          "name": "Back Screen Shadow",
          "position": { "x": 85, "y": 150 },
          "size": { "width": 760, "height": 1535 },
          "rotation": 0,
          "scale": 1,
          "shapeType": "rectangle",
          "fillColor": "#232653",
          "strokeColor": "transparent",
          "strokeWidth": 0,
          "borderRadius": 52,
          "fillOpacity": 0.12
        },
        {
          "id": "tpl_lt_ab2_back_screen",
          "type": "image",
          "name": "Back Screen",
          "position": { "x": 85, "y": 130 },
          "size": { "width": 760, "height": 1535 },
          "rotation": 0,
          "scale": 1,
          "imageSrc": "/data/projects/inboxly-screen-inbox.png",
          "imageAlt": "Skeleton app screen",
          "objectFit": "cover",
          "borderRadius": 52
        },
        {
          "id": "tpl_lt_ab2_front_shadow",
          "type": "shape",
          "name": "Front Screen Shadow",
          "position": { "x": 450, "y": 850 },
          "size": { "width": 780, "height": 1576 },
          "rotation": 0,
          "scale": 1,
          "shapeType": "rectangle",
          "fillColor": "#232653",
          "strokeColor": "transparent",
          "strokeWidth": 0,
          "borderRadius": 52,
          "fillOpacity": 0.12
        },
        {
          "id": "tpl_lt_ab2_front_screen",
          "type": "image",
          "name": "Front Screen",
          "position": { "x": 450, "y": 830 },
          "size": { "width": 780, "height": 1576 },
          "rotation": 0,
          "scale": 1,
          "imageSrc": "/data/projects/inboxly-screen-inbox.png",
          "imageAlt": "Skeleton app screen",
          "objectFit": "cover",
          "borderRadius": 52
        }
      ]
    },
    {
      "id": "tpl_lt_ab3",
      "name": "Boost Conversions",
      "position": { "x": 819, "y": 15 },
      "size": { "width": 1290, "height": 2796 },
      "backgroundColor": "#FBE5DE",
      "zoom": 1,
      "elements": [
        {
          "id": "tpl_lt_ab3_block",
          "type": "shape",
          "name": "Color Block",
          "position": { "x": 0, "y": 0 },
          "size": { "width": 1290, "height": 2000 },
          "rotation": 0,
          "scale": 1,
          "shapeType": "rectangle",
          "fillColor": "#F1512D",
          "strokeColor": "transparent",
          "strokeWidth": 0,
          "borderRadius": 0
        },
        {
          "id": "tpl_lt_ab3_screen_shadow",
          "type": "shape",
          "name": "Screen Shadow",
          "position": { "x": 195, "y": -90 },
          "size": { "width": 900, "height": 1818 },
          "rotation": 0,
          "scale": 1,
          "shapeType": "rectangle",
          "fillColor": "#232653",
          "strokeColor": "transparent",
          "strokeWidth": 0,
          "borderRadius": 56,
          "fillOpacity": 0.18
        },
        {
          "id": "tpl_lt_ab3_screen",
          "type": "image",
          "name": "Skeleton Screen",
          "position": { "x": 195, "y": -110 },
          "size": { "width": 900, "height": 1818 },
          "rotation": 0,
          "scale": 1,
          "imageSrc": "/data/projects/inboxly-screen-inbox.png",
          "imageAlt": "Skeleton app screen",
          "objectFit": "cover",
          "borderRadius": 56
        },
        {
          "id": "tpl_lt_ab3_text1",
          "type": "text",
          "name": "Headline Accent",
          "position": { "x": 50, "y": 2140 },
          "size": { "width": 1190, "height": 250 },
          "rotation": 0,
          "scale": 1,
          "content": "Boost\nconversions",
          "fontSize": 30,
          "color": "#F1512D",
          "fontFamily": "Bricolage Grotesque",
          "fontWeight": "700",
          "textAlign": "center",
          "lineHeight": 1.15
        },
        {
          "id": "tpl_lt_ab3_text2",
          "type": "text",
          "name": "Headline Rest",
          "position": { "x": 50, "y": 2390 },
          "size": { "width": 1190, "height": 130 },
          "rotation": 0,
          "scale": 1,
          "content": "by up to 35%",
          "fontSize": 30,
          "color": "#232653",
          "fontFamily": "Bricolage Grotesque",
          "fontWeight": "700",
          "textAlign": "center",
          "lineHeight": 1.15
        }
      ]
    },
    {
      "id": "tpl_lt_ab4",
      "name": "One Design",
      "position": { "x": 1221, "y": 15 },
      "size": { "width": 1290, "height": 2796 },
      "backgroundColor": "#6A62E1",
      "zoom": 1,
      "elements": [
        {
          "id": "tpl_lt_ab4_block",
          "type": "shape",
          "name": "Light Block",
          "position": { "x": 0, "y": 0 },
          "size": { "width": 1290, "height": 630 },
          "rotation": 0,
          "scale": 1,
          "shapeType": "rectangle",
          "fillColor": "#E3E3EE",
          "strokeColor": "transparent",
          "strokeWidth": 0,
          "borderRadius": 0
        },
        {
          "id": "tpl_lt_ab4_text1",
          "type": "text",
          "name": "Headline Accent",
          "position": { "x": 50, "y": 120 },
          "size": { "width": 1190, "height": 130 },
          "rotation": 0,
          "scale": 1,
          "content": "One design",
          "fontSize": 30,
          "color": "#6A62E1",
          "fontFamily": "Bricolage Grotesque",
          "fontWeight": "700",
          "textAlign": "center",
          "lineHeight": 1.15
        },
        {
          "id": "tpl_lt_ab4_text2",
          "type": "text",
          "name": "Headline Rest",
          "position": { "x": 50, "y": 250 },
          "size": { "width": 1190, "height": 250 },
          "rotation": 0,
          "scale": 1,
          "content": "for all of your\noutput sizes",
          "fontSize": 30,
          "color": "#232653",
          "fontFamily": "Bricolage Grotesque",
          "fontWeight": "700",
          "textAlign": "center",
          "lineHeight": 1.15
        },
        {
          "id": "tpl_lt_ab4_screen_shadow",
          "type": "shape",
          "name": "Screen Shadow",
          "position": { "x": 195, "y": 1030 },
          "size": { "width": 900, "height": 1818 },
          "rotation": 0,
          "scale": 1,
          "shapeType": "rectangle",
          "fillColor": "#232653",
          "strokeColor": "transparent",
          "strokeWidth": 0,
          "borderRadius": 56,
          "fillOpacity": 0.18
        },
        {
          "id": "tpl_lt_ab4_screen",
          "type": "image",
          "name": "Skeleton Screen",
          "position": { "x": 195, "y": 1010 },
          "size": { "width": 900, "height": 1818 },
          "rotation": 0,
          "scale": 1,
          "imageSrc": "/data/projects/inboxly-screen-inbox.png",
          "imageAlt": "Skeleton app screen",
          "objectFit": "cover",
          "borderRadius": 56
        }
      ]
    },
    {
      "id": "tpl_lt_ab5",
      "name": "Automatic Uploads",
      "position": { "x": 1623, "y": 15 },
      "size": { "width": 1290, "height": 2796 },
      "backgroundColor": "#E0F0E8",
      "zoom": 1,
      "elements": [
        {
          "id": "tpl_lt_ab5_block",
          "type": "shape",
          "name": "Color Block",
          "position": { "x": 0, "y": 0 },
          "size": { "width": 1290, "height": 2000 },
          "rotation": 0,
          "scale": 1,
          "shapeType": "rectangle",
          "fillColor": "#178B57",
          "strokeColor": "transparent",
          "strokeWidth": 0,
          "borderRadius": 0
        },
        {
          "id": "tpl_lt_ab5_screen_shadow",
          "type": "shape",
          "name": "Screen Shadow",
          "position": { "x": 195, "y": -90 },
          "size": { "width": 900, "height": 1818 },
          "rotation": 0,
          "scale": 1,
          "shapeType": "rectangle",
          "fillColor": "#232653",
          "strokeColor": "transparent",
          "strokeWidth": 0,
          "borderRadius": 56,
          "fillOpacity": 0.18
        },
        {
          "id": "tpl_lt_ab5_screen",
          "type": "image",
          "name": "Skeleton Screen",
          "position": { "x": 195, "y": -110 },
          "size": { "width": 900, "height": 1818 },
          "rotation": 0,
          "scale": 1,
          "imageSrc": "/data/projects/inboxly-screen-inbox.png",
          "imageAlt": "Skeleton app screen",
          "objectFit": "cover",
          "borderRadius": 56
        },
        {
          "id": "tpl_lt_ab5_text1",
          "type": "text",
          "name": "Headline Accent",
          "position": { "x": 50, "y": 2160 },
          "size": { "width": 1190, "height": 130 },
          "rotation": 0,
          "scale": 1,
          "content": "Automatic",
          "fontSize": 30,
          "color": "#178B57",
          "fontFamily": "Bricolage Grotesque",
          "fontWeight": "700",
          "textAlign": "center",
          "lineHeight": 1.15
        },
        {
          "id": "tpl_lt_ab5_text2",
          "type": "text",
          "name": "Headline Rest",
          "position": { "x": 50, "y": 2290 },
          "size": { "width": 1190, "height": 250 },
          "rotation": 0,
          "scale": 1,
          "content": "App Store\nuploads",
          "fontSize": 30,
          "color": "#232653",
          "fontFamily": "Bricolage Grotesque",
          "fontWeight": "700",
          "textAlign": "center",
          "lineHeight": 1.15
        }
      ]
    },
    {
      "id": "tpl_lt_ab6",
      "name": "Pixel Perfect",
      "position": { "x": 2025, "y": 15 },
      "size": { "width": 1290, "height": 2796 },
      "backgroundColor": "#F1512D",
      "zoom": 1,
      "elements": [
        {
          "id": "tpl_lt_ab6_block",
          "type": "shape",
          "name": "Light Block",
          "position": { "x": 0, "y": 0 },
          "size": { "width": 1290, "height": 630 },
          "rotation": 0,
          "scale": 1,
          "shapeType": "rectangle",
          "fillColor": "#FBE5DE",
          "strokeColor": "transparent",
          "strokeWidth": 0,
          "borderRadius": 0
        },
        {
          "id": "tpl_lt_ab6_text1",
          "type": "text",
          "name": "Headline Accent",
          "position": { "x": 50, "y": 120 },
          "size": { "width": 1190, "height": 130 },
          "rotation": 0,
          "scale": 1,
          "content": "Pixel perfect",
          "fontSize": 30,
          "color": "#F1512D",
          "fontFamily": "Bricolage Grotesque",
          "fontWeight": "700",
          "textAlign": "center",
          "lineHeight": 1.15
        },
        {
          "id": "tpl_lt_ab6_text2",
          "type": "text",
          "name": "Headline Rest",
          "position": { "x": 50, "y": 250 },
          "size": { "width": 1190, "height": 250 },
          "rotation": 0,
          "scale": 1,
          "content": "exports ready to\nupload",
          "fontSize": 30,
          "color": "#232653",
          "fontFamily": "Bricolage Grotesque",
          "fontWeight": "700",
          "textAlign": "center",
          "lineHeight": 1.15
        },
        {
          "id": "tpl_lt_ab6_screen_shadow",
          "type": "shape",
          "name": "Screen Shadow",
          "position": { "x": 195, "y": 1030 },
          "size": { "width": 900, "height": 1818 },
          "rotation": 0,
          "scale": 1,
          "shapeType": "rectangle",
          "fillColor": "#232653",
          "strokeColor": "transparent",
          "strokeWidth": 0,
          "borderRadius": 56,
          "fillOpacity": 0.18
        },
        {
          "id": "tpl_lt_ab6_screen",
          "type": "image",
          "name": "Skeleton Screen",
          "position": { "x": 195, "y": 1010 },
          "size": { "width": 900, "height": 1818 },
          "rotation": 0,
          "scale": 1,
          "imageSrc": "/data/projects/inboxly-screen-inbox.png",
          "imageAlt": "Skeleton app screen",
          "objectFit": "cover",
          "borderRadius": 56
        }
      ]
    },
    {
      "id": "tpl_lt_ab7",
      "name": "All Devices",
      "position": { "x": 2427, "y": 15 },
      "size": { "width": 1290, "height": 2796 },
      "backgroundColor": "#E3E3EE",
      "zoom": 1,
      "elements": [
        {
          "id": "tpl_lt_ab7_block",
          "type": "shape",
          "name": "Color Block",
          "position": { "x": 0, "y": 0 },
          "size": { "width": 1290, "height": 2000 },
          "rotation": 0,
          "scale": 1,
          "shapeType": "rectangle",
          "fillColor": "#6A62E1",
          "strokeColor": "transparent",
          "strokeWidth": 0,
          "borderRadius": 0
        },
        {
          "id": "tpl_lt_ab7_screen_shadow",
          "type": "shape",
          "name": "Screen Shadow",
          "position": { "x": 195, "y": -90 },
          "size": { "width": 900, "height": 1818 },
          "rotation": 0,
          "scale": 1,
          "shapeType": "rectangle",
          "fillColor": "#232653",
          "strokeColor": "transparent",
          "strokeWidth": 0,
          "borderRadius": 56,
          "fillOpacity": 0.18
        },
        {
          "id": "tpl_lt_ab7_screen",
          "type": "image",
          "name": "Skeleton Screen",
          "position": { "x": 195, "y": -110 },
          "size": { "width": 900, "height": 1818 },
          "rotation": 0,
          "scale": 1,
          "imageSrc": "/data/projects/inboxly-screen-inbox.png",
          "imageAlt": "Skeleton app screen",
          "objectFit": "cover",
          "borderRadius": 56
        },
        {
          "id": "tpl_lt_ab7_text1",
          "type": "text",
          "name": "Headline Accent",
          "position": { "x": 50, "y": 2160 },
          "size": { "width": 1190, "height": 130 },
          "rotation": 0,
          "scale": 1,
          "content": "All devices",
          "fontSize": 30,
          "color": "#6A62E1",
          "fontFamily": "Bricolage Grotesque",
          "fontWeight": "700",
          "textAlign": "center",
          "lineHeight": 1.15
        },
        {
          "id": "tpl_lt_ab7_text2",
          "type": "text",
          "name": "Headline Rest",
          "position": { "x": 50, "y": 2290 },
          "size": { "width": 1190, "height": 250 },
          "rotation": 0,
          "scale": 1,
          "content": "Apple & Android\napp release",
          "fontSize": 30,
          "color": "#232653",
          "fontFamily": "Bricolage Grotesque",
          "fontWeight": "700",
          "textAlign": "center",
          "lineHeight": 1.15
        }
      ]
    },
    {
      "id": "tpl_lt_ab8",
      "name": "Endless Layouts",
      "position": { "x": 2829, "y": 15 },
      "size": { "width": 1290, "height": 2796 },
      "backgroundColor": "#178B57",
      "zoom": 1,
      "elements": [
        {
          "id": "tpl_lt_ab8_block",
          "type": "shape",
          "name": "Light Block",
          "position": { "x": 0, "y": 0 },
          "size": { "width": 1290, "height": 630 },
          "rotation": 0,
          "scale": 1,
          "shapeType": "rectangle",
          "fillColor": "#E0F0E8",
          "strokeColor": "transparent",
          "strokeWidth": 0,
          "borderRadius": 0
        },
        {
          "id": "tpl_lt_ab8_text1",
          "type": "text",
          "name": "Headline Accent",
          "position": { "x": 50, "y": 120 },
          "size": { "width": 1190, "height": 130 },
          "rotation": 0,
          "scale": 1,
          "content": "Create endless",
          "fontSize": 30,
          "color": "#178B57",
          "fontFamily": "Bricolage Grotesque",
          "fontWeight": "700",
          "textAlign": "center",
          "lineHeight": 1.15
        },
        {
          "id": "tpl_lt_ab8_text2",
          "type": "text",
          "name": "Headline Rest",
          "position": { "x": 50, "y": 250 },
          "size": { "width": 1190, "height": 250 },
          "rotation": 0,
          "scale": 1,
          "content": "custom layouts\nand designs",
          "fontSize": 30,
          "color": "#232653",
          "fontFamily": "Bricolage Grotesque",
          "fontWeight": "700",
          "textAlign": "center",
          "lineHeight": 1.15
        },
        {
          "id": "tpl_lt_ab8_screen_shadow",
          "type": "shape",
          "name": "Screen Shadow",
          "position": { "x": 195, "y": 1030 },
          "size": { "width": 900, "height": 1818 },
          "rotation": 0,
          "scale": 1,
          "shapeType": "rectangle",
          "fillColor": "#232653",
          "strokeColor": "transparent",
          "strokeWidth": 0,
          "borderRadius": 56,
          "fillOpacity": 0.18
        },
        {
          "id": "tpl_lt_ab8_screen",
          "type": "image",
          "name": "Skeleton Screen",
          "position": { "x": 195, "y": 1010 },
          "size": { "width": 900, "height": 1818 },
          "rotation": 0,
          "scale": 1,
          "imageSrc": "/data/projects/inboxly-screen-inbox.png",
          "imageAlt": "Skeleton app screen",
          "objectFit": "cover",
          "borderRadius": 56
        }
      ]
    }
  ]
}
